geoDf.py
prep_acs.py
svi_data/__init__.py
svi_data/svi.py
svi_data-0.0.3.dist-info/LICENSE
svi_data-0.0.3.dist-info/METADATA
svi_data-0.0.3.dist-info/WHEEL
svi_data-0.0.3.dist-info/top_level.txt
svi_data-0.0.3.dist-info/RECORD
