Metadata-Version: 2.1
Name: svi-data
Version: 0.0.3
Summary: Download SVI (social vulnerability index) data from CDC
Home-page: https://github.com/apwheele/svi_data
Author: Andrew Palmer Wheeler
Author-email: apwheele@gmail.com
License: UNKNOWN
Platform: UNKNOWN
Classifier: Programming Language :: Python :: 3
Classifier: License :: OSI Approved :: MIT License
Classifier: Operating System :: OS Independent
Classifier: Topic :: Scientific/Engineering :: Information Analysis
Requires-Python: >=3.6
License-File: LICENSE
Requires-Dist: pandas
Requires-Dist: census
